{
  "plugin_version": "5.9.3",
  "linear": {
    "id": "ENG-1889",
    "url": "https://linear.app/shovels/issue/ENG-1889/shovels-cli-agent-first-rest-api-cli-go",
    "title": "Shovels CLI — Agent-first REST API CLI (Go)",
    "description": "Agent-first CLI for the Shovels REST API. Go + cobra. Single binary, JSON output, --limit N pagination, meaningful exit codes.",
    "branch": "luka/eng-1889-shovels-cli-agent-first-rest-api-cli-go",
    "created_at": "2026-02-27T15:43:56Z"
  },
  "execution": {
    "guard_mode": "codex",
    "user_instructions": "",
    "current_step": 4,
    "total_steps": 13
  },
  "steps": {
    "1": {
      "status": "approved",
      "range_base": "8955fdf96f15a250b9f628feeeb58cd234daa378",
      "head_sha": "eb7da6e9c9b11b9dc843a05b55230eaad925fb5f",
      "head_tree": "ce3cfc1748703734df29f874908cd7b4bae66480"
    },
    "2": {
      "status": "approved",
      "range_base": "eb7da6e9c9b11b9dc843a05b55230eaad925fb5f",
      "head_sha": "6df9c6139bde66c5ed5e8d8dc3bd84282851eec4",
      "head_tree": "5b0d691b1f43fa38b95064f12ef4c052217d0780"
    },
    "3": {
      "status": "approved",
      "range_base": "6df9c6139bde66c5ed5e8d8dc3bd84282851eec4",
      "head_sha": "be3911bf644ae80233da31b4df168e116233925c",
      "head_tree": "658e36a69935cee7951d88ab169bea77b0bace20"
    },
    "4": {
      "status": "in_progress",
      "range_base": "be3911bf644ae80233da31b4df168e116233925c",
      "head_sha": "91badb9b809e12b5fd116e7f876183f6788c8032",
      "head_tree": "7eebb5e03deb70e4aa2ce73345a1f69579384c7a"
    },
    "5": {
      "status": "pending",
      "range_base": null,
      "head_sha": null
    },
    "6": {
      "status": "pending",
      "range_base": null,
      "head_sha": null
    },
    "7": {
      "status": "pending",
      "range_base": null,
      "head_sha": null
    },
    "8": {
      "status": "pending",
      "range_base": null,
      "head_sha": null
    },
    "9": {
      "status": "pending",
      "range_base": null,
      "head_sha": null
    },
    "10": {
      "status": "pending",
      "range_base": null,
      "head_sha": null
    },
    "11": {
      "status": "pending",
      "range_base": null,
      "head_sha": null
    },
    "12": {
      "status": "pending",
      "range_base": null,
      "head_sha": null
    },
    "13": {
      "status": "pending",
      "range_base": null,
      "head_sha": null
    }
  }
}
